Metadata-Version: 2.1
Name: alibabacloud-oss-sdk-py2
Version: 0.0.2
Summary: Aliyun Tea OSS SDK Library for Python2
Home-page: https://github.com/aliyun/alibabacloud-oss-sdk/tree/master/python2
Author: Alibaba Cloud
Author-email: alibaba-cloud-sdk-dev-team@list.alibaba-inc.com
License: Apache License 2.0
Keywords: alibabacloud,oss,sdk,py2
Platform: any
Classifier: Development Status :: 4 - Beta
Classifier: Intended Audience :: Developers
Classifier: License :: OSI Approved :: Apache Software License
Classifier: Programming Language :: Python
Classifier: Programming Language :: Python :: 2
Classifier: Programming Language :: Python :: 2.7
Classifier: Topic :: Software Development
